README.md
enigma_aps.py
setup.py
enigma_aps.egg-info/PKG-INFO
enigma_aps.egg-info/SOURCES.txt
enigma_aps.egg-info/dependency_links.txt
enigma_aps.egg-info/requires.txt
enigma_aps.egg-info/top_level.txt