Metadata-Version: 2.1
Name: enigma_aps
Version: 1.0.4
Summary: Uma biblioteca que contém funções para cifrar e decifrar mensagens usando uma simulação da máquina enigma.
Home-page: https://github.com/gabrielfmendesm/enigma_aps
Author: Gabriel Mendes
Author-email: gabrielfmm@al.insper.edu.br
License: MIT
Requires-Dist: numpy
